get_pwbrowser_sync/__init__.py
get_pwbrowser_sync/config.py
get_pwbrowser_sync/get_pwbrowser_sync.py
get_pwbrowser_sync-0.1.3.dist-info/METADATA
get_pwbrowser_sync-0.1.3.dist-info/WHEEL
get_pwbrowser_sync-0.1.3.dist-info/RECORD
