Metadata-Version: 2.1
Name: get-pwbrowser-sync
Version: 0.1.3
Summary: Instantiate a playwright chromium (sync as opposed to async) browser
Home-page: https://github.com/ffreemt/get-pwbrowser-sync
Author: ffreemt
Requires-Python: >=3.7,<4.0
Classifier: Programming Language :: Python :: 3
Classifier: Programming Language :: Python :: 3.7
Classifier: Programming Language :: Python :: 3.8
Classifier: Programming Language :: Python :: 3.9
Classifier: Programming Language :: Python :: 3.10
Classifier: Programming Language :: Python :: 3.11
Requires-Dist: logzero (>=1.6.3,<2.0.0)
Requires-Dist: playwright[chromium] (>=1.24.0,<2.0.0)
Requires-Dist: pydantic[dotenv] (>=1.8.1,<2.0.0)
Requires-Dist: pyquery (>=1.4.3,<2.0.0)
Requires-Dist: typing-extensions (==4.7.1)
Project-URL: Repository, https://github.com/ffreemt/get-pwbrowser-sync
